fast_healthchecks/__init__.py
fast_healthchecks/compat.py
fast_healthchecks/models.py
fast_healthchecks/py.typed
fast_healthchecks/checks/__init__.py
fast_healthchecks/checks/_base.py
fast_healthchecks/checks/function.py
fast_healthchecks/checks/kafka.py
fast_healthchecks/checks/mongo.py
fast_healthchecks/checks/opensearch.py
fast_healthchecks/checks/rabbitmq.py
fast_healthchecks/checks/redis.py
fast_healthchecks/checks/types.py
fast_healthchecks/checks/url.py
fast_healthchecks/checks/postgresql/__init__.py
fast_healthchecks/checks/postgresql/asyncpg.py
fast_healthchecks/checks/postgresql/base.py
fast_healthchecks/checks/postgresql/psycopg.py
fast_healthchecks/integrations/__init__.py
fast_healthchecks/integrations/base.py
fast_healthchecks/integrations/fastapi.py
fast_healthchecks/integrations/faststream.py
fast_healthchecks/integrations/litestar.py
fast_healthchecks-0.2.4.dist-info/licenses/LICENSE
fast_healthchecks-0.2.4.dist-info/METADATA
fast_healthchecks-0.2.4.dist-info/WHEEL
fast_healthchecks-0.2.4.dist-info/top_level.txt
fast_healthchecks-0.2.4.dist-info/RECORD
