Metadata-Version: 2.4
Name: fast-healthchecks
Version: 0.2.4
Summary: FastHealthchecks
Author-email: Vladislav Shepilov <shepilov.v@protonmail.com>
Maintainer-email: Vladislav Shepilov <shepilov.v@protonmail.com>
License: MIT License
Project-URL: homepage, https://github.com/shepilov-vladislav/fast-healthchecks
Project-URL: documentation, https://shepilov-vladislav.github.io/fast-healthchecks/
Project-URL: source, https://github.com/shepilov-vladislav/fast-healthchecks
Project-URL: tracker, https://github.com/shepilov-vladislav/fast-healthchecks/issues
Keywords: healthcheck,library,fastapi,starlette,faststream,litestar,asyncpg,psycopg,redis,aio-pika,httpx,aiokafka,motor
Classifier: Development Status :: 1 - Planning
Classifier: Intended Audience :: Developers
Classifier: Topic :: Software Development :: Libraries
Classifier: Programming Language :: Python :: 3 :: Only
Classifier: Programming Language :: Python :: 3.10
Classifier: Programming Language :: Python :: 3.11
Classifier: Programming Language :: Python :: 3.12
Classifier: Programming Language :: Python :: 3.13
Classifier: License :: OSI Approved :: MIT License
Requires-Python: <4.0.0,>=3.10.0
License-File: LICENSE
Provides-Extra: pydantic
Requires-Dist: pydantic<3.0.0,>=2.11.9; extra == "pydantic"
Provides-Extra: asyncpg
Requires-Dist: asyncpg<1.0.0,>=0.30.0; extra == "asyncpg"
Provides-Extra: psycopg
Requires-Dist: psycopg<4.0.0,>=3.2.10; extra == "psycopg"
Provides-Extra: redis
Requires-Dist: redis<7.0.0,>=6.4.0; extra == "redis"
Provides-Extra: aio-pika
Requires-Dist: aio-pika<10.0.0,>=9.5.7; extra == "aio-pika"
Provides-Extra: httpx
Requires-Dist: httpx<1.0.0,>=0.28.1; extra == "httpx"
Provides-Extra: aiokafka
Requires-Dist: aiokafka<1.0.0,>=0.12.0; extra == "aiokafka"
Provides-Extra: motor
Requires-Dist: motor<4.0.0,>=3.7.1; extra == "motor"
Provides-Extra: fastapi
Requires-Dist: fastapi[standard]<1.0.0,>=0.116.2; extra == "fastapi"
Provides-Extra: faststream
Requires-Dist: faststream<1.0.0,>=0.5.48; extra == "faststream"
Provides-Extra: litestar
Requires-Dist: litestar<3.0.0,>=2.17.0; extra == "litestar"
Provides-Extra: msgspec
Requires-Dist: msgspec<1.0.0,>=0.19.0; extra == "msgspec"
Provides-Extra: opensearch
Requires-Dist: opensearch-py[async]<4.0.0,>=3.0.0; extra == "opensearch"
Dynamic: license-file
